sphinx_websequencediagrams.py
sphinx_websequencediagrams-0.3.4.dist-info/LICENSE
sphinx_websequencediagrams-0.3.4.dist-info/METADATA
sphinx_websequencediagrams-0.3.4.dist-info/WHEEL
sphinx_websequencediagrams-0.3.4.dist-info/entry_points.txt
sphinx_websequencediagrams-0.3.4.dist-info/top_level.txt
sphinx_websequencediagrams-0.3.4.dist-info/RECORD
