Metadata-Version: 2.1
Name: sphinx-websequencediagrams
Version: 0.3.4
Summary: Sphinx extension that integrates www.websequencediagrams.com
Home-page: https://github.com/MaxwellGBrown/sphinx-websequencediagrams
Author: Maxwell Brown
Author-email: maxwellgbrown@gmail.com
License: MIT
Platform: UNKNOWN
Requires-Dist: demjson (==2.2.4)
